{
  "project_info": {
    "project_number": "165912526335",
    "project_id": "comlckuyabcddbca5",
    "storage_bucket": "comlckuyabcddbca5.appspot.com"
  },
  "client": [
    {
      "client_info": {
        "mobilesdk_app_id": "1:165912526335:android:a27208ceaace7532f73bca",
        "android_client_info": {
          "package_name": "com.lckuyabcd.dbca"
        }
      },
      "oauth_client": [],
      "api_key": [
        {
          "current_key": "AIzaSyDblVpNWeYSyNffUGMpWao_0noY2ThB0yg"
        }
      ],
      "services": {
        "appinvite_service": {
          "other_platform_oauth_client": []
        }
      }
    }
  ],
  "configuration_version": "1"
}